remote_object/__init__.py
remote_object/client.py
remote_object/errors.py
remote_object/server.py
remote_object-0.2.4.dist-info/LICENSE
remote_object-0.2.4.dist-info/METADATA
remote_object-0.2.4.dist-info/WHEEL
remote_object-0.2.4.dist-info/top_level.txt
remote_object-0.2.4.dist-info/RECORD
