Metadata-Version: 2.1
Name: remote-object
Version: 0.2.4
Summary: A TCP-based server/client library for making method calls from a client to a python object on the server
Home-page: https://github.com/jonathanvanschenck/python-remote-object
Author: Jonathan D B Van Schenck
Author-email: vanschej@oregonstate.edu
License: UNKNOWN
Platform: UNKNOWN
Classifier: Programming Language :: Python :: 3
Classifier: License :: OSI Approved :: MIT License
Classifier: Operating System :: OS Independent
Requires-Python: >=3.6
Requires-Dist: cloudpickle (>=1.4.1)
